[
  {
    "name": "After 15 years",
    "id": "_15_Yrs",
    "days_after_birth_due": 0,
    "vaccines": [
      {
        "name": "TT 1",
        "type": "TT",
        "openmrs_date": {
          "parent_entity": "104528AAAAAAAAAAAAAAAAAAAAAAAAAAAAAA",
          "entity": "concept",
          "entity_id": "1410AAAAAAAAAAAAAAAAAAAAAAAAAAAAAAAA"
        },
        "openmrs_calculate": {
          "parent_entity": "104528AAAAAAAAAAAAAAAAAAAAAAAAAAAAAA",
          "entity": "concept",
          "entity_id": "1418AAAAAAAAAAAAAAAAAAAAAAAAAAAAAAAA",
          "calculation": 1
        },
        "schedule": {
          "due": [
            {
              "reference": "dob",
              "offset": "+15y",
              "window": "+100y"
            }
          ]
        }
      }
    ]
  },
  {
    "name": "4 Weeks after TD 1",
    "id": "_4_Wks",
    "days_after_birth_due": 28,
    "vaccines": [
      {
        "name": "TT 2",
        "type": "TT",
        "openmrs_date": {
          "parent_entity": "104528AAAAAAAAAAAAAAAAAAAAAAAAAAAAAA",
          "entity": "concept",
          "entity_id": "1410AAAAAAAAAAAAAAAAAAAAAAAAAAAAAAAA"
        },
        "openmrs_calculate": {
          "parent_entity": "104528AAAAAAAAAAAAAAAAAAAAAAAAAAAAAA",
          "entity": "concept",
          "entity_id": "1418AAAAAAAAAAAAAAAAAAAAAAAAAAAAAAAA",
          "calculation": 2
        },
        "schedule": {
          "due": [
            {
              "reference": "prerequisite",
              "prerequisite": "TT 1",
              "offset": "+28d",
              "window": "+14d"
            }
          ]
        }
      }
    ]
  },
  {
    "name": "26 Weeks after TD 2",
    "id": "_10_Wks",
    "days_after_birth_due": 180,
    "vaccines": [
      {
        "name": "TT 3",
        "type": "TT",
        "openmrs_date": {
          "parent_entity": "104528AAAAAAAAAAAAAAAAAAAAAAAAAAAAAA",
          "entity": "concept",
          "entity_id": "1410AAAAAAAAAAAAAAAAAAAAAAAAAAAAAAAA"
        },
        "openmrs_calculate": {
          "parent_entity": "104528AAAAAAAAAAAAAAAAAAAAAAAAAAAAAA",
          "entity": "concept",
          "entity_id": "1418AAAAAAAAAAAAAAAAAAAAAAAAAAAAAAAA",
          "calculation": 3
        },
        "schedule": {
          "due": [
            {
              "reference": "prerequisite",
              "prerequisite": "TT 2",
              "offset": "+182d",
              "window": "+14d"
            }
          ]
        }
      }
    ]
  },
  {
    "name": "1 year after TD 3",
    "id": "_14_Wks",
    "days_after_birth_due": 98,
    "vaccines": [
      {
        "name": "TT 4",
        "type": "TT",
        "openmrs_date": {
          "parent_entity": "104528AAAAAAAAAAAAAAAAAAAAAAAAAAAAAA",
          "entity": "concept",
          "entity_id": "1410AAAAAAAAAAAAAAAAAAAAAAAAAAAAAAAA"
        },
        "openmrs_calculate": {
          "parent_entity": "104528AAAAAAAAAAAAAAAAAAAAAAAAAAAAAA",
          "entity": "concept",
          "entity_id": "1418AAAAAAAAAAAAAAAAAAAAAAAAAAAAAAAA",
          "calculation": 4
        },
        "schedule": {
          "due": [
            {
              "reference": "prerequisite",
              "prerequisite": "TT 3",
              "offset": "+364d",
              "window": "+14d"
            }
          ]
        }
      }
    ]
  },
  {
    "name": "1 year after TD 4",
    "id": "_9_mnths",
    "days_after_birth_due": 274,
    "vaccines": [
      {
        "name": "TT 5",
        "type": "TT",
        "openmrs_date": {
          "parent_entity": "104528AAAAAAAAAAAAAAAAAAAAAAAAAAAAAA",
          "entity": "concept",
          "entity_id": "1410AAAAAAAAAAAAAAAAAAAAAAAAAAAAAAAA"
        },
        "openmrs_calculate": {
          "parent_entity": "104528AAAAAAAAAAAAAAAAAAAAAAAAAAAAAA",
          "entity": "concept",
          "entity_id": "1418AAAAAAAAAAAAAAAAAAAAAAAAAAAAAAAA",
          "calculation": 5
        },
        "schedule": {
          "due": [
            {
              "reference": "prerequisite",
              "prerequisite": "TT 4",
              "offset": "+364d",
              "window": "+14d"
            }
          ]
        }
      }
    ]
  }
]